pyspdx/__init__.py
pyspdx/license_exceptions.py
pyspdx/licenseids.py
pyspdx/parsing.py
pyspdx/py.typed
pyspdx-1.1.0.dist-info/COPYING
pyspdx-1.1.0.dist-info/METADATA
pyspdx-1.1.0.dist-info/WHEEL
pyspdx-1.1.0.dist-info/RECORD
