Metadata-Version: 2.3
Name: pyspdx
Version: 1.1.0
Summary: Validate SPDX expressions
License: GPL-2.0-only
Author: Checkmk GmbH
Author-email: info@checkmk.com
Requires-Python: >=3.8,<4.0
Classifier: License :: OSI Approved :: GNU General Public License v2 (GPLv2)
Classifier: Programming Language :: Python :: 3
Classifier: Programming Language :: Python :: 3.8
Classifier: Programming Language :: Python :: 3.9
Classifier: Programming Language :: Python :: 3.10
Classifier: Programming Language :: Python :: 3.11
Classifier: Programming Language :: Python :: 3.12
Classifier: Programming Language :: Python :: 3.13
Classifier: Typing :: Typed
Requires-Dist: pyparsing
Project-URL: Repository, https://github.com/checkmk/pyspdx
